kh_data_science/__init__.py
kh_data_science/cli.py
kh_data_science/downloader.py
kh_data_science/google_storage.py
kh_data_science/kh_data_science.py
kh_data_science-0.1.4.dist-info/AUTHORS.rst
kh_data_science-0.1.4.dist-info/METADATA
kh_data_science-0.1.4.dist-info/WHEEL
kh_data_science-0.1.4.dist-info/entry_points.txt
kh_data_science-0.1.4.dist-info/top_level.txt
kh_data_science-0.1.4.dist-info/RECORD
