Metadata-Version: 2.1
Name: kh-data-science
Version: 0.1.4
Summary: Functions for use within KisanHub's data science environments
Home-page: https://github.com/KisanHub/kh_data_science
Author: KisanHub Data Science
Author-email: ds@kisanhub.com
License: UNKNOWN
Keywords: kh_data_science
Platform: UNKNOWN
Classifier: Development Status :: 2 - Pre-Alpha
Classifier: Intended Audience :: Developers
Classifier: Natural Language :: English
Classifier: Programming Language :: Python :: 2
Classifier: Programming Language :: Python :: 2.7
Classifier: Programming Language :: Python :: 3
Classifier: Programming Language :: Python :: 3.4
Classifier: Programming Language :: Python :: 3.5
Classifier: Programming Language :: Python :: 3.6
Classifier: Programming Language :: Python :: 3.7
Requires-Dist: Click (>=6.0)
